CroFlow/__init__.py
CroFlow/cro_flow.py
tests/__init__.py
tests/coro_flow_test.py
CroFlow-0.0.1.dist-info/LICENSE
CroFlow-0.0.1.dist-info/METADATA
CroFlow-0.0.1.dist-info/WHEEL
CroFlow-0.0.1.dist-info/top_level.txt
CroFlow-0.0.1.dist-info/RECORD
