Metadata-Version: 2.1
Name: CroFlow
Version: 0.0.1
Summary: CroFlow is a Python library for running asynchronous coroutines concurrently, yielding results as soon as they are available. It supports both single-threaded and multi-threaded execution, offering flexibility for efficientlymanaging complex asynchronous tasks. handling exceptions and timeouts to optimize performance and manage complex workflows.
Author: Curtidor
Author-email: tannermatos18@gmail.com
Keywords: CroFlow,asynchronous,threading,parallel execution,coroutines,task management,performance optimization,Python 3
Classifier: Development Status :: 3 - Alpha
Classifier: Intended Audience :: Developers
Classifier: Programming Language :: Python :: 3
Classifier: Operating System :: Unix
Classifier: Operating System :: Microsoft :: Windows
License-File: LICENSE
Requires-Dist: pytest
Requires-Dist: setuptools~=65.5.1
